MANIFEST.in
README.md
setup.py
bin/manage-oracle-creds
epltoolset/__init__.py
epltoolset/pdConnection.py
epltoolset.egg-info/PKG-INFO
epltoolset.egg-info/SOURCES.txt
epltoolset.egg-info/dependency_links.txt
epltoolset.egg-info/requires.txt
epltoolset.egg-info/top_level.txt