Metadata-Version: 2.1
Name: epltoolset
Version: 0.3.2
Summary: Simplify Oracle ETL scripts
Home-page: http://github.com.robertpranney/epltoolset
Author: Robert Ranney
Author-email: robertpranney@gmail.com
License: UNKNOWN
Platform: UNKNOWN
Classifier: Development Status :: 3 - Alpha
Classifier: Programming Language :: Python :: 3.6
Classifier: License :: OSI Approved :: MIT License
Classifier: Operating System :: OS Independent
Classifier: Topic :: Database :: Front-Ends
Requires-Python: >=3.6
